startgarlic/__init__.py
startgarlic/cli.py
startgarlic/core.py
startgarlic/redirect_service.py
startgarlic/api/main.py
startgarlic/api/server.py
startgarlic/utils_py/__init__.py
startgarlic/utils_py/analytics.py
startgarlic/utils_py/auction.py
startgarlic/utils_py/config.py
startgarlic/utils_py/database.py
startgarlic/utils_py/embeddings.py
startgarlic/utils_py/prompts.py
startgarlic/utils_py/secure_credentials.py
startgarlic-0.1.30.dist-info/METADATA
startgarlic-0.1.30.dist-info/WHEEL
startgarlic-0.1.30.dist-info/entry_points.txt
startgarlic-0.1.30.dist-info/top_level.txt
startgarlic-0.1.30.dist-info/RECORD
