Metadata-Version: 2.4
Name: startgarlic
Version: 0.1.30
Summary: A RAG-based company information retrieval system
Author-email: Bogdan Ciolac <bogdan@startgarlic.com>, May Elshater <may@startgarlic.com>
License: MIT
Project-URL: Homepage, https://github.com/startgarlic/MVP
Classifier: Programming Language :: Python :: 3
Classifier: Operating System :: OS Independent
Classifier: Development Status :: 3 - Alpha
Requires-Python: >=3.7
Requires-Dist: numpy<2.0.0,>=1.23.5
Requires-Dist: pandas>=2.0.0
Requires-Dist: supabase>=2.11.0
Requires-Dist: httpx<0.29.0,>=0.26.0
Requires-Dist: websockets<14.0,>=11.0
Requires-Dist: requests<3.0.0,>=2.27.0
Requires-Dist: python-dotenv
Requires-Dist: sentence-transformers
Requires-Dist: langchain>=0.2.15
Requires-Dist: langchain-community>=0.2.15
Requires-Dist: langchain-huggingface>=0.0.3
Requires-Dist: fastapi>=0.68.0
Requires-Dist: uvicorn>=0.15.0
